setup.py
uvwxyz/__init__.py
uvwxyz/uvwxyz.py
uvwxyz.egg-info/PKG-INFO
uvwxyz.egg-info/SOURCES.txt
uvwxyz.egg-info/dependency_links.txt
uvwxyz.egg-info/requires.txt
uvwxyz.egg-info/top_level.txt