Metadata-Version: 1.1
Name: uvwxyz
Version: 1.1.1
Summary: Calculate XYZ and UVW coordinates
Home-page: https://github.com/dr-rodriguez/uvwxyz.git
Author: David Rodriguez
Author-email: drodriguez1@amnh.org
License: MIT
Keywords: astrophysics
Platform: UNKNOWN
Classifier: Development Status :: 4 - Beta
Classifier: Intended Audience :: Science/Research
Classifier: License :: OSI Approved :: MIT License
Classifier: Programming Language :: Python
